trackbear_api/__init__.py
trackbear_api/_apiclient.py
trackbear_api/_goalclient.py
trackbear_api/_leaderboardclient.py
trackbear_api/_projectclient.py
trackbear_api/_statclient.py
trackbear_api/_tagclient.py
trackbear_api/_tallyclient.py
trackbear_api/enums.py
trackbear_api/exceptions.py
trackbear_api/models.py
trackbear_api/py.typed
trackbear_api/trackbearclient.py
trackbear_api-0.0.8.dist-info/METADATA
trackbear_api-0.0.8.dist-info/WHEEL
trackbear_api-0.0.8.dist-info/licenses/LICENSE
trackbear_api-0.0.8.dist-info/RECORD
