Metadata-Version: 2.4
Name: trackbear-api
Version: 0.0.8
Summary: Python library for synchronous HTTP calls to the Trackbear API (https://help.trackbear.app/api)
Project-URL: homepage, https://github.com/Preocts/trackbear-api
Author-email: Preocts <preocts@preocts.com>
License-Expression: MIT
License-File: LICENSE
Classifier: Programming Language :: Python :: 3
Classifier: Programming Language :: Python :: 3 :: Only
Classifier: Programming Language :: Python :: Implementation :: CPython
Requires-Python: >=3.10
Requires-Dist: requests>=2.32.5
